driver_pcap_parser/__init__.py
driver_pcap_parser/cli.py
driver_pcap_parser/models.py
driver_pcap_parser/parsers.py
driver_pcap_parser-0.1.24.dist-info/AUTHORS.rst
driver_pcap_parser-0.1.24.dist-info/LICENSE
driver_pcap_parser-0.1.24.dist-info/METADATA
driver_pcap_parser-0.1.24.dist-info/WHEEL
driver_pcap_parser-0.1.24.dist-info/entry_points.txt
driver_pcap_parser-0.1.24.dist-info/top_level.txt
driver_pcap_parser-0.1.24.dist-info/RECORD
