Metadata-Version: 2.1
Name: driver-pcap-parser
Version: 0.1.24
Summary: Python PCAP file parser for FC drivers
Home-page: https://github.com/andrke/driver_pcap_parser
Author: Andres Kepler
Author-email: andres.kepler@entigo.com
License: MIT license
Keywords: driver_pcap_parser
Platform: UNKNOWN
Classifier: Development Status :: 2 - Pre-Alpha
Classifier: Intended Audience :: Developers
Classifier: License :: OSI Approved :: MIT License
Classifier: Natural Language :: English
Classifier: Programming Language :: Python :: 3
Classifier: Programming Language :: Python :: 3.5
Classifier: Programming Language :: Python :: 3.6
Classifier: Programming Language :: Python :: 3.7
Classifier: Programming Language :: Python :: 3.8
Requires-Python: >=3.5
Requires-Dist: scapy
Requires-Dist: logstash-formatter
